amarillo/__init__.py
amarillo/plugins/__init__.py
amarillo/plugins/gtfs_export/__init__.py
amarillo/plugins/gtfs_export/config.py
amarillo/plugins/gtfs_export/gtfs.py
amarillo/plugins/gtfs_export/gtfs_constants.py
amarillo/plugins/gtfs_export/gtfs_export.py
amarillo/plugins/gtfs_export/gtfs_generator.py
amarillo/plugins/gtfs_export/router.py
amarillo/plugins/gtfs_export/gtfsrt/__init__.py
amarillo/plugins/gtfs_export/gtfsrt/gtfs_realtime_pb2.py
amarillo/plugins/gtfs_export/gtfsrt/realtime_extension_pb2.py
amarillo/plugins/gtfs_export/models/__init__.py
amarillo/plugins/gtfs_export/models/gtfs.py
amarillo/plugins/gtfs_export/tests/__init__.py
amarillo/plugins/gtfs_export/tests/test_gtfs.py
amarillo_grfs_exporter-2.0.2.dist-info/LICENSE
amarillo_grfs_exporter-2.0.2.dist-info/METADATA
amarillo_grfs_exporter-2.0.2.dist-info/WHEEL
amarillo_grfs_exporter-2.0.2.dist-info/top_level.txt
amarillo_grfs_exporter-2.0.2.dist-info/RECORD
