Metadata-Version: 2.1
Name: amarillo-grfs-exporter
Version: 2.0.2
Summary: GRFS export plugin for Amarillo
License:                     GNU AFFERO GENERAL PUBLIC LICENSE
License-File: LICENSE
Requires-Dist: amarillo
